odoo/addons/auth_ldap_attribute_sync/README.rst
odoo/addons/auth_ldap_attribute_sync/__init__.py
odoo/addons/auth_ldap_attribute_sync/__manifest__.py
odoo/addons/auth_ldap_attribute_sync/models/__init__.py
odoo/addons/auth_ldap_attribute_sync/models/ldap_attribute_mapping.py
odoo/addons/auth_ldap_attribute_sync/models/res_company_ldap.py
odoo/addons/auth_ldap_attribute_sync/models/res_users.py
odoo/addons/auth_ldap_attribute_sync/readme/CONFIGURE.rst
odoo/addons/auth_ldap_attribute_sync/readme/CONTRIBUTORS.rst
odoo/addons/auth_ldap_attribute_sync/readme/DESCRIPTION.rst
odoo/addons/auth_ldap_attribute_sync/security/ir.model.access.csv
odoo/addons/auth_ldap_attribute_sync/static/description/icon.png
odoo/addons/auth_ldap_attribute_sync/static/description/index.html
odoo/addons/auth_ldap_attribute_sync/tests/__init__.py
odoo/addons/auth_ldap_attribute_sync/tests/test_auth_ldap_attribute_sync.py
odoo/addons/auth_ldap_attribute_sync/views/ldap_attribute_mapping_views.xml
odoo/addons/auth_ldap_attribute_sync/views/res_company_ldap_views.xml
odoo12_addon_auth_ldap_attribute_sync-12.0.1.0.0.dist-info/METADATA
odoo12_addon_auth_ldap_attribute_sync-12.0.1.0.0.dist-info/RECORD
odoo12_addon_auth_ldap_attribute_sync-12.0.1.0.0.dist-info/WHEEL
odoo12_addon_auth_ldap_attribute_sync-12.0.1.0.0.dist-info/top_level.txt
