Metadata-Version: 2.1
Name: odoo12-addon-auth-ldap-attribute-sync
Version: 12.0.1.0.0
Summary: Allows to update users’ fields from LDAP attributes
Home-page: https://github.com/OCA/server-auth
Author: Braibean Apps, Odoo Community Association (OCA)
Author-email: support@odoo-community.org
License: AGPL-3
Platform: UNKNOWN
Classifier: Programming Language :: Python
Classifier: Framework :: Odoo
Classifier: License :: OSI Approved :: GNU Affero General Public License v3
Requires-Python: >=3.5
Requires-Dist: odoo (<12.1dev,>=12.0a)
Requires-Dist: python-ldap
